pvai/__init__.py
pvai/analysis.py
pvai/cleaning.py
pvai/.ipynb_checkpoints/__init__-checkpoint.py
pvai/.ipynb_checkpoints/analysis-checkpoint.py
pvai/.ipynb_checkpoints/cleaning-checkpoint.py
pvai-0.0.3.dist-info/METADATA
pvai-0.0.3.dist-info/WHEEL
pvai-0.0.3.dist-info/licenses/LICENSE.txt
pvai-0.0.3.dist-info/RECORD
