Metadata-Version: 2.1
Name: pvai
Version: 0.0.3
Summary: Data processing package
Project-URL: Homepage, https://github.com/pypa/sampleproject
Project-URL: Bug Tracker, https://github.com/pypa/sampleproject/issues
Author-email: Francis De Voogt <francisdevoogt@hotmail.com>
License-File: LICENSE.txt
Classifier: License :: OSI Approved :: MIT License
Classifier: Operating System :: OS Independent
Classifier: Programming Language :: Python :: 3
Requires-Python: >=3.7
